{"Alder Flycatcher":{"0":"05-20","1":"05-31","2":"07-07"},"American Black Duck":{"0":"05-07","1":"05-31","2":"09-18"},"American Bittern":{"0":"04-29","1":"05-14","2":"08-31"},"American Crow":{"0":"02-28","1":"03-21","2":"06-12"},"American Goldfinch":{"0":"05-10","1":"05-21","2":"06-06"},"American Kestrel":{"0":"04-02","1":"05-07","2":"06-13"},"American Pipit":{"0":"04-30","1":"05-31","2":"07-13"},"American Redstart":{"0":"05-11","1":"05-31","2":"07-13"},"American Robin":{"0":"04-02","1":"05-14","2":"08-26"},"American Wigeon":{"0":"04-13","1":"04-30","2":"09-13"},"American Woodcock":{"0":"04-07","1":"04-14","2":"06-07"},"American Golden-Plover":{"0":"05-17","1":"05-31","2":"06-23"},"American Herring Gull":{"0":"03-16","1":"04-07","2":"09-13"},"American Tree Sparrow":{"0":"03-30","1":"04-21","2":"05-12"},"American White Pelican":{"0":"04-18","1":"05-21","2":"09-06"},"Arctic Tern":{"0":"05-21","1":"05-31","2":"08-01"},"American Three-toed Woodpecker":{"0":"05-30","1":"05-31","2":"06-02"},"Bay-breasted Warbler":{"0":"05-14","1":"05-31","2":"07-19"},"Baird's Sandpiper":{"0":"05-15","1":"05-21","2":"05-30"},"Bald Eagle":{"0":"02-24","1":"03-21","2":"06-13"},"Baltimore Oriole":{"0":"05-07","1":"05-21","2":"06-09"},"Bank Swallow":{"0":"05-19","1":"05-31","2":"08-12"},"Barn Swallow":{"0":"05-05","1":"05-21","2":"09-04"},"Black-and-white Warbler":{"0":"05-04","1":"05-21","2":"09-08"},"Belted Kingfisher":{"0":"04-16","1":"05-07","2":"10-09"},"Black-billed Cuckoo":{"0":"05-15","1":"05-21","2":"05-30"},"Black-billed Magpie":{"0":"02-18","1":"02-28","2":"03-04"},"Black-bellied Plover":{"0":"05-16","1":"05-31","2":"06-14"},"Blackburnian Warbler":{"0":"05-08","1":"05-21","2":"08-30"},"Black-backed Woodpecker":{"0":"05-14","1":"05-14","2":"05-14"},"Black-capped Chickadee":{"0":"02-27","1":"02-28","2":"03-01"},"Blackpoll Warbler":{"0":"05-09","1":"05-21","2":"07-13"},"Black Scoter":{"0":"05-01","1":"05-07","2":"05-13"},"Black Tern":{"0":"05-21","1":"05-31","2":"06-07"},"Blue Jay":{"0":"02-25","1":"02-28","2":"03-02"},"Brown-headed Cowbird":{"0":"04-15","1":"05-07","2":"06-10"},"Bobolink":{"0":"05-15","1":"05-21","2":"08-04"},"Bohemian Waxwing":{"0":"02-26","1":"02-28","2":"03-09"},"Bonaparte's Gull":{"0":"04-28","1":"05-14","2":"09-09"},"Boreal Chickadee":{"0":"02-28","1":"02-28","2":"02-28"},"Boreal Owl":{"0":"03-02","1":"03-31","2":"04-07"},"Brant":{"0":"05-23","1":"05-31","2":"06-29"},"Barred Owl":{"0":"04-03","1":"04-14","2":"04-27"},"Brewer's Blackbird":{"0":"04-23","1":"05-07","2":"06-11"},"Brown Creeper":{"0":"04-30","1":"04-30","2":"04-30"},"Brown Thrasher":{"0":"04-22","1":"04-30","2":"06-15"},"Broad-winged Hawk":{"0":"04-21","1":"05-07","2":"09-12"},"Black-throated Blue Warbler":{"0":"05-15","1":"05-31","2":"06-06"},"Black-throated Green Warbler":{"0":"05-08","1":"05-21","2":"06-13"},"Bufflehead":{"0":"04-10","1":"04-30","2":"06-09"},"Blue-headed Vireo":{"0":"05-05","1":"05-21","2":"09-08"},"Bullock's Oriole":{"0":"05-08","1":"05-14","2":"05-20"},"Blue-winged Teal":{"0":"04-16","1":"05-14","2":"06-14"},"Cackling Goose":{"0":"04-15","1":"04-21","2":"04-29"},"Cape May Warbler":{"0":"05-08","1":"05-21","2":"06-22"},"Canada Goose":{"0":"03-08","1":"04-07","2":"10-17"},"Canvasback":{"0":"04-21","1":"05-14","2":"06-07"},"Canada Warbler":{"0":"05-16","1":"05-31","2":"08-29"},"Caspian Tern":{"0":"05-15","1":"05-21","2":"05-30"},"Cedar Waxwing":{"0":"05-17","1":"05-31","2":"09-14"},"Chipping Sparrow":{"0":"04-28","1":"05-14","2":"09-03"},"Chimney Swift":{"0":"05-21","1":"05-31","2":"06-07"},"Chestnut-sided Warbler":{"0":"05-11","1":"05-21","2":"09-02"},"Clay-colored Sparrow":{"0":"05-01","1":"05-14","2":"07-20"},"Cliff Swallow":{"0":"05-05","1":"05-21","2":"08-06"},"Common Goldeneye":{"0":"03-14","1":"04-21","2":"06-04"},"Common Grackle":{"0":"04-09","1":"04-30","2":"06-08"},"Common Loon":{"0":"04-17","1":"05-21","2":"10-07"},"Common Merganser":{"0":"03-26","1":"05-21","2":"09-05"},"Common Nighthawk":{"0":"05-15","1":"05-31","2":"09-10"},"Common Raven":{"0":"02-28","1":"02-28","2":"02-28"},"Common Tern":{"0":"05-06","1":"05-21","2":"09-11"},"Common Yellowthroat":{"0":"05-14","1":"05-31","2":"08-06"},"Connecticut Warbler":{"0":"05-21","1":"05-31","2":"07-02"},"Cooper's Hawk":{"0":"05-16","1":"05-31","2":"06-14"},"Dark-eyed Junco":{"0":"03-29","1":"04-14","2":"05-12"},"Dickcissel":{"0":"05-23","1":"05-31","2":"06-06"},"Double-crested Cormorant":{"0":"04-09","1":"05-14","2":"09-13"},"Downy Woodpecker":{"0":"02-28","1":"02-28","2":"02-28"},"Dunlin":{"0":"05-11","1":"05-31","2":"08-14"},"Eared Grebe":{"0":"05-15","1":"05-21","2":"05-30"},"Eastern Bluebird":{"0":"05-02","1":"05-21","2":"08-07"},"Eastern Kingbird":{"0":"05-09","1":"05-21","2":"08-29"},"Eastern Meadowlark":{"0":"05-15","1":"05-21","2":"05-30"},"Eastern Phoebe":{"0":"04-21","1":"05-31","2":"09-05"},"Eastern Towhee":{"0":"02-28","1":"02-28","2":"02-28"},"Eastern Whip-poor-will":{"0":"04-28","1":"05-31","2":"07-06"},"Eastern Wood-Pewee":{"0":"05-15","1":"05-31","2":"09-07"},"Eurasian Siskin":{"0":"05-01","1":"05-07","2":"05-13"},"European Starling":{"0":"03-23","1":"05-14","2":"06-08"},"Eurasian Tree Sparrow":{"0":"04-08","1":"04-14","2":"04-20"},"Evening Grosbeak":{"0":"02-27","1":"02-28","2":"03-01"},"Fox Sparrow":{"0":"04-07","1":"04-14","2":"05-05"},"Gadwall":{"0":"05-13","1":"05-31","2":"06-12"},"Gray-crowned Rosy-Finch":{"0":"02-22","1":"02-28","2":"03-01"},"Green-winged Teal":{"0":"04-08","1":"04-30","2":"10-15"},"Golden-crowned Kinglet":{"0":"04-10","1":"05-31","2":"10-14"},"Golden-crowned Sparrow":{"0":"04-14","1":"04-14","2":"04-14"},"Golden Eagle":{"0":"03-15","1":"03-21","2":"03-29"},"Golden-winged Warbler":{"0":"05-15","1":"05-31","2":"06-19"},"Great Blue Heron":{"0":"03-31","1":"04-07","2":"09-19"},"Great Crested Flycatcher":{"0":"05-22","1":"05-31","2":"06-08"},"Great Egret":{"0":"04-15","1":"04-21","2":"04-29"},"Greater Scaup":{"0":"04-21","1":"04-30","2":"05-18"},"Greater Yellowlegs":{"0":"04-14","1":"04-30","2":"10-18"},"Great Gray Owl":{"0":"02-19","1":"02-28","2":"03-02"},"Great Horned Owl":{"0":"03-25","1":"03-31","2":"04-05"},"Gray Catbird":{"0":"05-09","1":"05-31","2":"06-21"},"Canada Jay":{"0":"02-28","1":"02-28","2":"02-28"},"Greater White-fronted Goose":{"0":"04-15","1":"04-21","2":"04-29"},"Gray-cheeked Thrush":{"0":"05-08","1":"05-14","2":"06-02"},"Hairy Woodpecker":{"0":"02-24","1":"02-28","2":"03-04"},"Harris's Sparrow":{"0":"05-01","1":"05-07","2":"05-20"},"Hermit Thrush":{"0":"05-07","1":"05-31","2":"08-02"},"Hooded Merganser":{"0":"03-23","1":"04-21","2":"05-31"},"Horned Grebe":{"0":"04-17","1":"05-07","2":"05-13"},"Horned Lark":{"0":"05-21","1":"05-31","2":"07-20"},"House Finch":{"0":"04-22","1":"04-30","2":"05-11"},"House Sparrow":{"0":"05-29","1":"05-31","2":"06-01"},"Northern House Wren":{"0":"05-09","1":"05-31","2":"06-30"},"Hudsonian Godwit":{"0":"05-18","1":"05-31","2":"08-16"},"Indigo Bunting":{"0":"05-08","1":"05-14","2":"05-29"},"Killdeer":{"0":"04-12","1":"05-14","2":"08-04"},"Lapland Longspur":{"0":"05-09","1":"05-31","2":"07-04"},"Lark Bunting":{"0":"05-23","1":"05-31","2":"06-06"},"Lesser Black-backed Gull":{"0":"05-08","1":"05-14","2":"05-20"},"Least Flycatcher":{"0":"05-08","1":"05-31","2":"08-29"},"Least Sandpiper":{"0":"05-07","1":"05-14","2":"09-04"},"LeConte's Sparrow":{"0":"05-03","1":"05-31","2":"08-19"},"Lesser Scaup":{"0":"04-15","1":"04-30","2":"05-29"},"Lesser Yellowlegs":{"0":"04-22","1":"05-14","2":"05-24"},"Lincoln's Sparrow":{"0":"05-04","1":"05-31","2":"09-26"},"Little Gull":{"0":"05-08","1":"05-14","2":"05-20"},"Long-billed Dowitcher":{"0":"05-01","1":"05-07","2":"05-13"},"Long-eared Owl":{"0":"04-08","1":"04-14","2":"05-02"},"Long-tailed Duck":{"0":"05-23","1":"05-31","2":"07-12"},"Magnolia Warbler":{"0":"05-09","1":"05-31","2":"08-07"},"Mallard":{"0":"03-24","1":"04-21","2":"09-14"},"Marbled Godwit":{"0":"05-15","1":"05-31","2":"06-06"},"Marsh Wren":{"0":"05-15","1":"05-21","2":"05-30"},"Merlin":{"0":"03-20","1":"04-30","2":"10-10"},"Mourning Dove":{"0":"04-09","1":"04-30","2":"06-11"},"Mourning Warbler":{"0":"05-15","1":"05-31","2":"07-30"},"Nashville Warbler":{"0":"05-06","1":"05-31","2":"09-07"},"Northern Hawk Owl":{"0":"03-21","1":"03-21","2":"03-21"},"Northern Cardinal":{"0":"02-28","1":"02-28","2":"02-28"},"Northern Flicker":{"0":"04-13","1":"04-30","2":"10-01"},"American Goshawk":{"0":"03-11","1":"03-14","2":"03-21"},"Northern Harrier":{"0":"03-28","1":"04-30","2":"09-07"},"Northern Mockingbird":{"0":"05-17","1":"05-31","2":"06-11"},"Northern Parula":{"0":"05-07","1":"05-21","2":"07-21"},"Northern Pintail":{"0":"04-03","1":"04-30","2":"08-19"},"Northern Shoveler":{"0":"04-16","1":"05-14","2":"09-14"},"Northern Shrike":{"0":"02-27","1":"02-28","2":"03-01"},"Northern Waterthrush":{"0":"05-08","1":"05-31","2":"07-14"},"Northern Rough-winged Swallow":{"0":"05-15","1":"05-21","2":"05-30"},"Northern Saw-whet Owl":{"0":"03-14","1":"04-14","2":"05-06"},"Olive-sided Flycatcher":{"0":"05-15","1":"05-21","2":"08-06"},"Orange-crowned Warbler":{"0":"05-05","1":"05-14","2":"07-13"},"Osprey":{"0":"04-12","1":"04-30","2":"08-31"},"Ovenbird":{"0":"05-07","1":"05-21","2":"07-17"},"Pacific Loon":{"0":"05-23","1":"05-31","2":"07-14"},"Palm Warbler":{"0":"04-30","1":"05-14","2":"07-13"},"Parasitic Jaeger":{"0":"05-23","1":"05-31","2":"07-14"},"Pectoral Sandpiper":{"0":"05-04","1":"05-14","2":"05-29"},"Peregrine Falcon":{"0":"05-23","1":"05-31","2":"08-14"},"Philadelphia Vireo":{"0":"05-15","1":"05-31","2":"07-13"},"Pied-billed Grebe":{"0":"03-29","1":"04-30","2":"06-13"},"Pileated Woodpecker":{"0":"02-24","1":"02-28","2":"03-06"},"Pine Grosbeak":{"0":"02-28","1":"02-28","2":"02-28"},"Pine Siskin":{"0":"02-18","1":"03-07","2":"04-16"},"Pine Warbler":{"0":"05-03","1":"05-31","2":"06-11"},"Piping Plover":{"0":"05-23","1":"05-31","2":"06-06"},"Purple Finch":{"0":"02-25","1":"05-14","2":"05-28"},"Purple Martin":{"0":"05-23","1":"05-31","2":"06-12"},"Red-breasted Merganser":{"0":"04-16","1":"05-07","2":"07-06"},"Red-breasted Nuthatch":{"0":"02-26","1":"02-28","2":"03-07"},"Red-bellied Woodpecker":{"0":"04-26","1":"04-30","2":"05-09"},"Red Crossbill":{"0":"02-19","1":"02-28","2":"03-15"},"Redhead":{"0":"04-12","1":"05-14","2":"06-14"},"Red Knot":{"0":"05-23","1":"05-31","2":"06-12"},"Redpoll":{"0":"02-22","1":"02-28","2":"03-13"},"Red-eyed Vireo":{"0":"05-15","1":"05-31","2":"09-05"},"Red-headed Woodpecker":{"0":"05-23","1":"05-31","2":"06-06"},"Red-necked Grebe":{"0":"04-17","1":"04-30","2":"06-12"},"Red-necked Phalarope":{"0":"05-21","1":"05-31","2":"07-07"},"Red-tailed Hawk":{"0":"03-22","1":"03-31","2":"09-14"},"Red-throated Loon":{"0":"05-17","1":"05-31","2":"07-17"},"Red-winged Blackbird":{"0":"04-08","1":"05-14","2":"06-15"},"Ring-billed Gull":{"0":"03-20","1":"04-07","2":"06-15"},"Ring-necked Duck":{"0":"04-11","1":"04-30","2":"06-18"},"Rose-breasted Grosbeak":{"0":"05-03","1":"05-14","2":"06-10"},"Rock Pigeon":{"0":"03-21","1":"03-21","2":"03-21"},"Rough-legged Hawk":{"0":"03-31","1":"04-14","2":"05-03"},"Ruby-throated Hummingbird":{"0":"05-08","1":"05-21","2":"06-11"},"Ruby-crowned Kinglet":{"0":"04-20","1":"05-31","2":"07-12"},"Ruddy Duck":{"0":"04-24","1":"05-14","2":"06-15"},"Ruddy Turnstone":{"0":"05-23","1":"05-31","2":"06-13"},"Ruffed Grouse":{"0":"04-22","1":"05-07","2":"05-29"},"Rusty Blackbird":{"0":"04-10","1":"04-30","2":"05-13"},"Sandhill Crane":{"0":"04-06","1":"05-21","2":"09-30"},"Sanderling":{"0":"05-23","1":"05-31","2":"06-07"},"Savannah Sparrow":{"0":"05-01","1":"05-14","2":"09-28"},"Scarlet Tanager":{"0":"05-17","1":"05-31","2":"06-07"},"Sedge Wren":{"0":"05-04","1":"05-14","2":"07-30"},"Semipalmated Plover":{"0":"05-14","1":"05-21","2":"09-06"},"Semipalmated Sandpiper":{"0":"05-14","1":"05-31","2":"06-30"},"Short-billed Dowitcher":{"0":"05-08","1":"05-14","2":"05-21"},"Short-eared Owl":{"0":"05-21","1":"05-31","2":"07-29"},"Sharp-shinned Hawk":{"0":"04-10","1":"04-21","2":"05-20"},"Sharp-tailed Grouse":{"0":"03-11","1":"03-14","2":"03-20"},"Smith's Longspur":{"0":"05-21","1":"05-31","2":"07-19"},"Snow Bunting":{"0":"03-12","1":"04-14","2":"04-27"},"Snow Goose":{"0":"04-01","1":"04-07","2":"04-18"},"Snowy Owl":{"0":"04-08","1":"04-14","2":"04-20"},"Solitary Sandpiper":{"0":"05-01","1":"05-14","2":"09-10"},"Song Sparrow":{"0":"04-11","1":"05-21","2":"09-05"},"Sora":{"0":"05-07","1":"05-14","2":"09-04"},"Spotted Sandpiper":{"0":"05-03","1":"05-21","2":"08-29"},"Spruce Grouse":{"0":"05-06","1":"05-07","2":"05-09"},"Stilt Sandpiper":{"0":"05-08","1":"05-14","2":"05-20"},"Surf Scoter":{"0":"05-01","1":"05-07","2":"05-13"},"Swamp Sparrow":{"0":"04-28","1":"05-31","2":"10-04"},"Swainson's Thrush":{"0":"05-15","1":"05-31","2":"07-31"},"Tennessee Warbler":{"0":"05-11","1":"05-31","2":"07-14"},"Townsend's Solitaire":{"0":"02-28","1":"02-28","2":"02-28"},"Tree Swallow":{"0":"04-19","1":"05-14","2":"07-27"},"Trumpeter Swan":{"0":"03-09","1":"03-31","2":"06-14"},"Tundra Swan":{"0":"04-19","1":"05-31","2":"07-14"},"Turkey Vulture":{"0":"04-05","1":"05-14","2":"10-03"},"Upland Sandpiper":{"0":"05-15","1":"05-21","2":"05-30"},"Veery":{"0":"05-15","1":"05-31","2":"07-18"},"Vesper Sparrow":{"0":"05-01","1":"05-14","2":"06-24"},"Virginia Rail":{"0":"05-18","1":"05-31","2":"08-27"},"Warbling Vireo":{"0":"05-08","1":"05-14","2":"05-20"},"Western Grebe":{"0":"05-01","1":"05-07","2":"05-13"},"Western Kingbird":{"0":"05-23","1":"05-31","2":"06-06"},"Western Meadowlark":{"0":"05-23","1":"05-31","2":"06-07"},"Western Tanager":{"0":"04-22","1":"04-30","2":"05-06"},"White-breasted Nuthatch":{"0":"02-28","1":"02-28","2":"02-28"},"White-crowned Sparrow":{"0":"04-30","1":"05-07","2":"05-21"},"Whimbrel":{"0":"05-20","1":"05-31","2":"08-01"},"White-rumped Sandpiper":{"0":"05-16","1":"05-31","2":"06-14"},"White-throated Sparrow":{"0":"04-23","1":"05-14","2":"10-17"},"White-winged Crossbill":{"0":"02-18","1":"02-28","2":"03-02"},"White-winged Dove":{"0":"04-16","1":"04-30","2":"05-09"},"White-winged Scoter":{"0":"04-29","1":"05-14","2":"05-31"},"Wilson's Phalarope":{"0":"05-05","1":"05-14","2":"06-09"},"Willow Ptarmigan":{"0":"05-21","1":"05-31","2":"07-11"},"Wilson's Snipe":{"0":"04-20","1":"05-31","2":"08-16"},"Winter Wren":{"0":"04-24","1":"05-31","2":"08-02"},"Wilson's Warbler":{"0":"05-10","1":"05-31","2":"09-10"},"Wood Duck":{"0":"04-04","1":"04-21","2":"10-21"},"Wood Thrush":{"0":"05-15","1":"05-21","2":"05-30"},"American Coot":{"0":"04-21","1":"05-14","2":"06-12"},"Iceland Gull":{"0":"03-22","1":"03-31","2":"04-06"},"Yellow-bellied Flycatcher":{"0":"05-20","1":"05-31","2":"07-18"},"Yellow-bellied Sapsucker":{"0":"04-08","1":"05-14","2":"07-07"},"Yellow-headed Blackbird":{"0":"04-18","1":"05-14","2":"06-12"},"Yellow Warbler":{"0":"05-09","1":"05-31","2":"08-07"},"Yellow-rumped Warbler":{"0":"04-21","1":"05-31","2":"10-07"}}